fastbot/__init__.py
fastbot/_version.py
fastbot/core.py
fastbot/json.py
fastbot/main.py
fastbot/memcached.py
fastbot/redis.py
fastbot/responses.py
fastbot-0.0.3.dist-info/METADATA
fastbot-0.0.3.dist-info/WHEEL
fastbot-0.0.3.dist-info/top_level.txt
fastbot-0.0.3.dist-info/RECORD
