Metadata-Version: 2.1
Name: fastbot
Version: 0.0.3
Summary: An sdk for building enterprise-grade conversational experiences
Home-page: https://github.com/getfastbot/python
Author: Allen
Author-email: allen@atlabs.dev
License: Proprietary License
Project-URL: Documentation, https://github.com/getfastbot/python
Project-URL: Source, https://github.com/getfastbot/python
Platform: UNKNOWN
Classifier: Development Status :: 5 - Production/Stable
Classifier: Intended Audience :: Developers
Classifier: Natural Language :: English
Classifier: License :: Other/Proprietary License
Classifier: Programming Language :: Python
Classifier: Programming Language :: Python :: 3 :: Only
Classifier: Programming Language :: Python :: 3
Classifier: Programming Language :: Python :: 3.6
Classifier: Programming Language :: Python :: 3.7
Classifier: Programming Language :: Python :: 3.8
Classifier: Programming Language :: Python :: 3.9
Requires-Python: >=3.6
Provides-Extra: all
Requires-Dist: redis ; extra == 'all'
Requires-Dist: pymemcache ; extra == 'all'
Provides-Extra: memcached
Requires-Dist: pymemcache ; extra == 'memcached'
Provides-Extra: redis
Requires-Dist: redis ; extra == 'redis'
